[
 {
  "trends": [
   {
    "name": "Ellen White",
    "url": "http://twitter.com/search?q=%22Ellen+White%22",
    "promoted_content": null,
    "query": "%22Ellen+White%22",
    "tweet_volume": null
   },
   {
    "name": "Bobby Shmurda",
    "url": "http://twitter.com/search?q=%22Bobby+Shmurda%22",
    "promoted_content": null,
    "query": "%22Bobby+Shmurda%22",
    "tweet_volume": 427226
   },
   {
    "name": "#hiring",
    "url": "http://twitter.com/search?q=%23hiring",
    "promoted_content": null,
    "query": "%23hiring",
    "tweet_volume": null
   },
   {
    "name": "Taunton",
    "url": "http://twitter.com/search?q=Taunton",
    "promoted_content": null,
    "query": "Taunton",
    "tweet_volume": null
   },
   {
    "name": "Holyrood",
    "url": "http://twitter.com/search?q=Holyrood",
    "promoted_content": null,
    "query": "Holyrood",
    "tweet_volume": null
   },
   {
    "name": "MC Hammer",
    "url": "http://twitter.com/search?q=%22MC+Hammer%22",
    "promoted_content": null,
    "query": "%22MC+Hammer%22",
    "tweet_volume": 13129
   },
   {
    "name": "#WorldBookDay",
    "url": "http://twitter.com/search?q=%23WorldBookDay",
    "promoted_content": null,
    "query": "%23WorldBookDay",
    "tweet_volume": null
   },
   {
    "name": "#ghetts4number1",
    "url": "http://twitter.com/search?q=%23ghetts4number1",
    "promoted_content": null,
    "query": "%23ghetts4number1",
    "tweet_volume": null
   },
   {
    "name": "#TuesdayThoughts",
    "url": "http://twitter.com/search?q=%23TuesdayThoughts",
    "promoted_content": null,
    "query": "%23TuesdayThoughts",
    "tweet_volume": null
   },
   {
    "name": "#MyFirstStream",
    "url": "http://twitter.com/search?q=%23MyFirstStream",
    "promoted_content": null,
    "query": "%23MyFirstStream",
    "tweet_volume": null
   },
   {
    "name": "sunmi",
    "url": "http://twitter.com/search?q=sunmi",
    "promoted_content": null,
    "query": "sunmi",
    "tweet_volume": 99078
   },
   {
    "name": "The Simpsons",
    "url": "http://twitter.com/search?q=%22The+Simpsons%22",
    "promoted_content": null,
    "query": "%22The+Simpsons%22",
    "tweet_volume": null
   },
   {
    "name": "btob",
    "url": "http://twitter.com/search?q=btob",
    "promoted_content": null,
    "query": "btob",
    "tweet_volume": 219025
   },
   {
    "name": "Nagelsmann",
    "url": "http://twitter.com/search?q=Nagelsmann",
    "promoted_content": null,
    "query": "Nagelsmann",
    "tweet_volume": null
   },
   {
    "name": "Family Guy",
    "url": "http://twitter.com/search?q=%22Family+Guy%22",
    "promoted_content": null,
    "query": "%22Family+Guy%22",
    "tweet_volume": null
   },
   {
    "name": "Unite",
    "url": "http://twitter.com/search?q=Unite",
    "promoted_content": null,
    "query": "Unite",
    "tweet_volume": 63484
   },
   {
    "name": "International Women's Day",
    "url": "http://twitter.com/search?q=%22International+Women%27s+Day%22",
    "promoted_content": null,
    "query": "%22International+Women%27s+Day%22",
    "tweet_volume": null
   },
   {
    "name": "Fairtrade",
    "url": "http://twitter.com/search?q=Fairtrade",
    "promoted_content": null,
    "query": "Fairtrade",
    "tweet_volume": null
   },
   {
    "name": "Favourite",
    "url": "http://twitter.com/search?q=Favourite",
    "promoted_content": null,
    "query": "Favourite",
    "tweet_volume": 148713
   },
   {
    "name": "Coldplay",
    "url": "http://twitter.com/search?q=Coldplay",
    "promoted_content": null,
    "query": "Coldplay",
    "tweet_volume": 106756
   },
   {
    "name": "Fix You",
    "url": "http://twitter.com/search?q=%22Fix+You%22",
    "promoted_content": null,
    "query": "%22Fix+You%22",
    "tweet_volume": 182594
   },
   {
    "name": "Nicola Sturgeon",
    "url": "http://twitter.com/search?q=%22Nicola+Sturgeon%22",
    "promoted_content": null,
    "query": "%22Nicola+Sturgeon%22",
    "tweet_volume": 24792
   },
   {
    "name": "Anna Rothery",
    "url": "http://twitter.com/search?q=%22Anna+Rothery%22",
    "promoted_content": null,
    "query": "%22Anna+Rothery%22",
    "tweet_volume": null
   },
   {
    "name": "Solidarity Anna",
    "url": "http://twitter.com/search?q=%22Solidarity+Anna%22",
    "promoted_content": null,
    "query": "%22Solidarity+Anna%22",
    "tweet_volume": null
   },
   {
    "name": "Ruth Davidson",
    "url": "http://twitter.com/search?q=%22Ruth+Davidson%22",
    "promoted_content": null,
    "query": "%22Ruth+Davidson%22",
    "tweet_volume": null
   },
   {
    "name": "Days Gone",
    "url": "http://twitter.com/search?q=%22Days+Gone%22",
    "promoted_content": null,
    "query": "%22Days+Gone%22",
    "tweet_volume": 14456
   },
   {
    "name": "Disney",
    "url": "http://twitter.com/search?q=Disney",
    "promoted_content": null,
    "query": "Disney",
    "tweet_volume": 175708
   },
   {
    "name": "Gordon McQueen",
    "url": "http://twitter.com/search?q=%22Gordon+McQueen%22",
    "promoted_content": null,
    "query": "%22Gordon+McQueen%22",
    "tweet_volume": null
   },
   {
    "name": "PSVR",
    "url": "http://twitter.com/search?q=PSVR",
    "promoted_content": null,
    "query": "PSVR",
    "tweet_volume": null
   },
   {
    "name": "Crown Office",
    "url": "http://twitter.com/search?q=%22Crown+Office%22",
    "promoted_content": null,
    "query": "%22Crown+Office%22",
    "tweet_volume": 14456
   },
   {
    "name": "Level 3",
    "url": "http://twitter.com/search?q=%22Level+3%22",
    "promoted_content": null,
    "query": "%22Level+3%22",
    "tweet_volume": 25930
   },
   {
    "name": "Maddi",
    "url": "http://twitter.com/search?q=Maddi",
    "promoted_content": null,
    "query": "Maddi",
    "tweet_volume": 11476
   },
   {
    "name": "Tier 3",
    "url": "http://twitter.com/search?q=%22Tier+3%22",
    "promoted_content": null,
    "query": "%22Tier+3%22",
    "tweet_volume": 39568
   },
   {
    "name": "End of April",
    "url": "http://twitter.com/search?q=%22End+of+April%22",
    "promoted_content": null,
    "query": "%22End+of+April%22",
    "tweet_volume": null
   },
   {
    "name": "Sony",
    "url": "http://twitter.com/search?q=Sony",
    "promoted_content": null,
    "query": "Sony",
    "tweet_volume": 58781
   },
   {
    "name": "Neil Robertson",
    "url": "http://twitter.com/search?q=%22Neil+Robertson%22",
    "promoted_content": null,
    "query": "%22Neil+Robertson%22",
    "tweet_volume": null
   },
   {
    "name": "Mayor of Liverpool",
    "url": "http://twitter.com/search?q=%22Mayor+of+Liverpool%22",
    "promoted_content": null,
    "query": "%22Mayor+of+Liverpool%22",
    "tweet_volume": null
   },
   {
    "name": "Erica",
    "url": "http://twitter.com/search?q=Erica",
    "promoted_content": null,
    "query": "Erica",
    "tweet_volume": 30160
   },
   {
    "name": "Shark",
    "url": "http://twitter.com/search?q=Shark",
    "promoted_content": null,
    "query": "Shark",
    "tweet_volume": 34857
   },
   {
    "name": "Salmond",
    "url": "http://twitter.com/search?q=Salmond",
    "promoted_content": null,
    "query": "Salmond",
    "tweet_volume": 49084
   },
   {
    "name": "Goodison",
    "url": "http://twitter.com/search?q=Goodison",
    "promoted_content": null,
    "query": "Goodison",
    "tweet_volume": null
   },
   {
    "name": "Zlatan",
    "url": "http://twitter.com/search?q=Zlatan",
    "promoted_content": null,
    "query": "Zlatan",
    "tweet_volume": null
   },
   {
    "name": "Miele",
    "url": "http://twitter.com/search?q=Miele",
    "promoted_content": null,
    "query": "Miele",
    "tweet_volume": null
   },
   {
    "name": "Starlink",
    "url": "http://twitter.com/search?q=Starlink",
    "promoted_content": null,
    "query": "Starlink",
    "tweet_volume": null
   },
   {
    "name": "Dyson",
    "url": "http://twitter.com/search?q=Dyson",
    "promoted_content": null,
    "query": "Dyson",
    "tweet_volume": null
   },
   {
    "name": "Robbie Williams",
    "url": "http://twitter.com/search?q=%22Robbie+Williams%22",
    "promoted_content": null,
    "query": "%22Robbie+Williams%22",
    "tweet_volume": null
   },
   {
    "name": "Jim Ryan",
    "url": "http://twitter.com/search?q=%22Jim+Ryan%22",
    "promoted_content": null,
    "query": "%22Jim+Ryan%22",
    "tweet_volume": null
   },
   {
    "name": "Tether",
    "url": "http://twitter.com/search?q=Tether",
    "promoted_content": null,
    "query": "Tether",
    "tweet_volume": 30131
   }
  ],
  "as_of": "2021-02-23T16:57:58Z",
  "created_at": "2021-02-22T13:17:20Z",
  "locations": [
   {
    "name": "Birmingham",
    "woeid": 12723
   }
  ]
 }
]